PrimarySchoolMath/APPconfig.py
PrimarySchoolMath/App.py
PrimarySchoolMath/PrintPreview.py
PrimarySchoolMath/Psmrcddup.py
PrimarySchoolMath/__init__.py
PrimarySchoolMath/utils/PSM_help.py
PrimarySchoolMath/utils/__init__.py
PrimarySchoolMath-1.0.4.dist-info/LICENSE
PrimarySchoolMath-1.0.4.dist-info/METADATA
PrimarySchoolMath-1.0.4.dist-info/WHEEL
PrimarySchoolMath-1.0.4.dist-info/top_level.txt
PrimarySchoolMath-1.0.4.dist-info/RECORD
