Metadata-Version: 2.1
Name: PrimarySchoolMath
Version: 1.0.4
Summary: 小学生口算题的小应用
Home-page: https://github.com/bosichong/PrimarySchoolMathematics
Author: J.sky
Author-email: bosichong@qq.com
License: UNKNOWN
Platform: UNKNOWN
Classifier: Programming Language :: Python :: 3
Classifier: License :: OSI Approved :: Apache Software License
Classifier: Operating System :: OS Independent
